re_edge_gpt/__init__.py
re_edge_gpt/__main__.py
re_edge_gpt/api/__init__.py
re_edge_gpt/api/main_flask.py
re_edge_gpt/api/re_edge_gpt_blueprint.py
re_edge_gpt/api/swagger_config.py
re_edge_gpt/chat/__init__.py
re_edge_gpt/chat/chathub.py
re_edge_gpt/chat/constants.py
re_edge_gpt/chat/conversation.py
re_edge_gpt/chat/conversation_style.py
re_edge_gpt/chat/locale.py
re_edge_gpt/chat/proxy.py
re_edge_gpt/chat/re_edge_gpt.py
re_edge_gpt/chat/request.py
re_edge_gpt/image/__init__.py
re_edge_gpt/image/image_genearation.py
re_edge_gpt/image/upload_image.py
re_edge_gpt/plugins/__init__.py
re_edge_gpt/plugins/suno.py
re_edge_gpt/ui/__init__.py
re_edge_gpt/ui/chat/__init__.py
re_edge_gpt/ui/chat/chat_thread.py
re_edge_gpt/ui/chat/input_dialog.py
re_edge_gpt/ui/chat/main_ui.py
re_edge_gpt/ui/chat/main_widget.py
re_edge_gpt/ui/chat/speech_to_text.py
re_edge_gpt/ui/chat/toast.py
re_edge_gpt/utils/__init__.py
re_edge_gpt/utils/utilities.py
re_edge_gpt/utils/exception/__init__.py
re_edge_gpt/utils/exception/exception_message.py
re_edge_gpt/utils/exception/exceptions.py
re_edge_gpt_dev-0.0.55.dist-info/LICENSE
re_edge_gpt_dev-0.0.55.dist-info/METADATA
re_edge_gpt_dev-0.0.55.dist-info/WHEEL
re_edge_gpt_dev-0.0.55.dist-info/top_level.txt
re_edge_gpt_dev-0.0.55.dist-info/RECORD
